wowool/apps/snippet/__init__.py
wowool/apps/snippet/config.py
wowool/snippet/__init__.py
wowool/snippet/app_id.py
wowool/snippet/snippet.py
wowool_snippet-2.1.2.dist-info/METADATA
wowool_snippet-2.1.2.dist-info/WHEEL
wowool_snippet-2.1.2.dist-info/top_level.txt
wowool_snippet-2.1.2.dist-info/RECORD
