Metadata-Version: 2.4
Name: wowool-snippet
Version: 2.1.2
Summary: The Wowool Snippet Package
Home-page: https://www.wowool.com/
Author: Wowool
Author-email: info@wowool.com
Requires-Python: >=3.11
Requires-Dist: wowool-sdk
Dynamic: author
Dynamic: author-email
Dynamic: description
Dynamic: description-content-type
Dynamic: home-page
Dynamic: requires-dist
Dynamic: requires-python
Dynamic: summary
